<?xml version="1.0" encoding="utf-8" ?><dwsync><file name="donate.png" server="ks3319042.kimsufi.com/httpdocs/" local="3576778334" remote="3577711380" Dst="-1" /><file name="duplicate-post-common.php" server="ks3319042.kimsufi.com/httpdocs/" local="3576778334" remote="3577711380" Dst="-1" /><file name="duplicate-post-admin.php" server="ks3319042.kimsufi.com/httpdocs/" local="3576778334" remote="3577711380" Dst="-1" /><file name="duplicate-post-options.php" server="ks3319042.kimsufi.com/httpdocs/" local="3576778334" remote="3577711380" Dst="-1" /><file name="duplicate-post.css" server="ks3319042.kimsufi.com/httpdocs/" local="3576778334" remote="3577711380" Dst="-1" /><file name="duplicate-post.php" server="ks3319042.kimsufi.com/httpdocs/" local="3576778334" remote="3577711380" Dst="-1" /><file name="gpl-2.0.txt" server="ks3319042.kimsufi.com/httpdocs/" local="3576778334" remote="3577711380" Dst="-1" /><file name="readme.txt" server="ks3319042.kimsufi.com/httpdocs/" local="3576778334" remote="3577711380" Dst="-1" /></dwsync>