<?xml version="1.0" encoding="utf-8" ?><dwsync><file name="404.php" server="ks3319042.kimsufi.com/httpdocs/" local="3559029487" remote="3552627000" Dst="-1" /><file name="category.php" server="ks3319042.kimsufi.com/httpdocs/" local="3559030341" remote="3559030320" Dst="-1" /><file name="footer.php" server="ks3319042.kimsufi.com/httpdocs/" local="3568194305" remote="318763443961090932" Dst="-1" /><file name="functions.php" server="ks3319042.kimsufi.com/httpdocs/" local="3568188028" remote="318763443961084512" Dst="-1" /><file name="gulpfile.js" server="ks3319042.kimsufi.com/httpdocs/" local="3559029488" remote="3552627000" Dst="-1" /><file name="header.php" server="ks3319042.kimsufi.com/httpdocs/" local="3568194875" remote="318763443961092012" Dst="-1" /><file name="index.php" server="ks3319042.kimsufi.com/httpdocs/" local="3559029489" remote="3552627000" Dst="-1" /><file name="license.txt" server="ks3319042.kimsufi.com/httpdocs/" local="3559029489" remote="3552627000" Dst="-1" /><file name="package.json" server="ks3319042.kimsufi.com/httpdocs/" local="3559029489" remote="3552627000" Dst="-1" /><file name="page_home.php" server="ks3319042.kimsufi.com/httpdocs/" local="3559029489" remote="3552627000" Dst="-1" /><file name="page_livre.php" server="ks3319042.kimsufi.com/httpdocs/" local="3559029489" remote="3552627060" Dst="-1" /><file name="page_texte.php" server="ks3319042.kimsufi.com/httpdocs/" local="3559029489" remote="3552627060" Dst="-1" /><file name="page_tmp.php" server="ks3319042.kimsufi.com/httpdocs/" local="3559029489" remote="3552628800" Dst="-1" /><file name="screenshot.png" server="ks3319042.kimsufi.com/httpdocs/" local="3559029490" remote="3552627060" Dst="-1" /><file name="single.php" server="ks3319042.kimsufi.com/httpdocs/" local="3568199759" remote="318763443961096272" Dst="-1" /><file name="style.css" server="ks3319042.kimsufi.com/httpdocs/" local="3559029490" remote="3552627060" Dst="-1" /></dwsync>